rdf2g/__init__.py
rdf2g/access.py
rdf2g/retrieve.py
rdf2g/transform.py
rdf2g/update.py
test/__init__.py
test/test_bnode_data.py
test/test_graph_creation.py
test/test_operations.py
rdf2gremlin-0.1.38.dist-info/LICENSE
rdf2gremlin-0.1.38.dist-info/METADATA
rdf2gremlin-0.1.38.dist-info/WHEEL
rdf2gremlin-0.1.38.dist-info/top_level.txt
rdf2gremlin-0.1.38.dist-info/RECORD
