Metadata-Version: 2.1
Name: rdf2gremlin
Version: 0.1.38
Summary: It has never been easier to transform your RDF data into a property graph based on TinkerPop-Gremlin.
Home-page: https://github.com/costezki/rdf2gremlin
Author: Eugeniu Costetchi
Author-email: costezki.eugen@gmail.com
Maintainer: Eugeniu Costetchi
Maintainer-email: costezki.eugen@gmail.com
License: UNKNOWN
Keywords: RDF,Gremlin,load,tinkerpop,tinkerpop3,rdf-gremlin,serialisation,
Platform: any
Classifier: Development Status :: 3 - Alpha
Classifier: Programming Language :: Python
Classifier: Programming Language :: Python :: 3
Classifier: Programming Language :: Python :: 3.6
Classifier: Programming Language :: Python :: 3.7
Classifier: Programming Language :: Python :: 3.8
Classifier: License :: OSI Approved :: GNU General Public License v3 (GPLv3)
Classifier: Operating System :: OS Independent
Classifier: Programming Language :: Python :: 3
Classifier: Topic :: Utilities
Classifier: Intended Audience :: Developers
Classifier: Topic :: Software Development :: Libraries :: Python Modules
Classifier: Operating System :: OS Independent
Classifier: Natural Language :: English
Requires-Python: >=3.6
Requires-Dist: uuid
Requires-Dist: rdflib
Requires-Dist: pathlib
Requires-Dist: gremlinpython
Requires-Dist: tornado
Requires-Dist: sphinx
Requires-Dist: sphinxcontrib-apidoc
Requires-Dist: myst-parser
Provides-Extra: test
Requires-Dist: coverage ; extra == 'test'
Requires-Dist: pytest ; extra == 'test'
Requires-Dist: pytest-cov ; extra == 'test'
